tag_fields/__init__.py
tag_fields/admin.py
tag_fields/apps.py
tag_fields/forms.py
tag_fields/managers.py
tag_fields/models.py
tag_fields/serializers.py
tag_fields/utils.py
tag_fields/views.py
tag_fields/locale/ar/LC_MESSAGES/django.mo
tag_fields/locale/ar/LC_MESSAGES/django.po
tag_fields/locale/cs/LC_MESSAGES/django.mo
tag_fields/locale/cs/LC_MESSAGES/django.po
tag_fields/locale/da/LC_MESSAGES/django.mo
tag_fields/locale/da/LC_MESSAGES/django.po
tag_fields/locale/de/LC_MESSAGES/django.mo
tag_fields/locale/de/LC_MESSAGES/django.po
tag_fields/locale/el/LC_MESSAGES/django.mo
tag_fields/locale/el/LC_MESSAGES/django.po
tag_fields/locale/en/LC_MESSAGES/django.mo
tag_fields/locale/en/LC_MESSAGES/django.po
tag_fields/locale/eo/LC_MESSAGES/django.mo
tag_fields/locale/eo/LC_MESSAGES/django.po
tag_fields/locale/es/LC_MESSAGES/django.mo
tag_fields/locale/es/LC_MESSAGES/django.po
tag_fields/locale/fa/LC_MESSAGES/django.mo
tag_fields/locale/fa/LC_MESSAGES/django.po
tag_fields/locale/fi/LC_MESSAGES/django.mo
tag_fields/locale/fi/LC_MESSAGES/django.po
tag_fields/locale/fr/LC_MESSAGES/django.mo
tag_fields/locale/fr/LC_MESSAGES/django.po
tag_fields/locale/he/LC_MESSAGES/django.mo
tag_fields/locale/he/LC_MESSAGES/django.po
tag_fields/locale/it/LC_MESSAGES/django.mo
tag_fields/locale/it/LC_MESSAGES/django.po
tag_fields/locale/ja/LC_MESSAGES/django.mo
tag_fields/locale/ja/LC_MESSAGES/django.po
tag_fields/locale/nb/LC_MESSAGES/django.mo
tag_fields/locale/nb/LC_MESSAGES/django.po
tag_fields/locale/nl/LC_MESSAGES/django.mo
tag_fields/locale/nl/LC_MESSAGES/django.po
tag_fields/locale/pt_BR/LC_MESSAGES/django.mo
tag_fields/locale/pt_BR/LC_MESSAGES/django.po
tag_fields/locale/ru/LC_MESSAGES/django.mo
tag_fields/locale/ru/LC_MESSAGES/django.po
tag_fields/locale/tr/LC_MESSAGES/django.mo
tag_fields/locale/tr/LC_MESSAGES/django.po
tag_fields/locale/uk/LC_MESSAGES/django.mo
tag_fields/locale/uk/LC_MESSAGES/django.po
tag_fields/locale/zh_Hans/LC_MESSAGES/django.mo
django_tag_fields-4.1.0.dist-info/LICENSE
django_tag_fields-4.1.0.dist-info/WHEEL
django_tag_fields-4.1.0.dist-info/METADATA
django_tag_fields-4.1.0.dist-info/RECORD
