Metadata-Version: 2.1
Name: django-tag-fields
Version: 4.1.0
Summary: Add field tags to a Django project
Keywords: Django,django,django tagging
Author-email: Alex Gaynor <alex.gaynor@gmail.com>
Maintainer-email: Mark Sevelj <mark.sevelj@dunwright.com.au>
Requires-Python: >=3.6
Classifier: Development Status :: 1 - Planning
Classifier: Environment :: Web Environment
Classifier: Framework :: Django
Classifier: Framework :: Django :: 3.2
Classifier: Framework :: Django :: 4.0
Classifier: Framework :: Django :: 4.1
Classifier: Framework :: Django :: 4.2
Classifier: Intended Audience :: Developers
Classifier: License :: OSI Approved :: BSD License
Classifier: Operating System :: OS Independent
Classifier: Programming Language :: Python
Classifier: Programming Language :: Python :: 3.6
Classifier: Programming Language :: Python :: 3.7
Classifier: Programming Language :: Python :: 3.8
Classifier: Programming Language :: Python :: 3.9
Classifier: Programming Language :: Python :: 3.10
Classifier: Programming Language :: Python :: 3.11
Requires-Dist: Django>=3.2
Project-URL: Documentation, https://django-tag-fields.readthedocs.io
Project-URL: Repository, https://github.com/imAsparky/django-tag-fields
Project-URL: Tracker, https://github.com/imAsparky/django-tag-fields/issues
